RuanjianGoujianShijian01/README.md
RuanjianGoujianShijian01/__init__.py
RuanjianGoujianShijian01/__main__.py
RuanjianGoujianShijian01/file.epub
RuanjianGoujianShijian01/index.html
RuanjianGoujianShijian01/css/__init__.py
RuanjianGoujianShijian01/css/annotations.css
RuanjianGoujianShijian01/css/main.css
RuanjianGoujianShijian01/css/normalize.css
RuanjianGoujianShijian01/css/popup.css
RuanjianGoujianShijian01/font/__init__.py
RuanjianGoujianShijian01/font/fontello.eot
RuanjianGoujianShijian01/font/fontello.svg
RuanjianGoujianShijian01/font/fontello.ttf
RuanjianGoujianShijian01/font/fontello.woff
RuanjianGoujianShijian01/img/__init__.py
RuanjianGoujianShijian01/img/annotator-glyph-sprite.png
RuanjianGoujianShijian01/img/annotator-icon-sprite.png
RuanjianGoujianShijian01/img/apple-touch-icon.png
RuanjianGoujianShijian01/img/cancelfullscreen.png
RuanjianGoujianShijian01/img/close.png
RuanjianGoujianShijian01/img/fullscreen.png
RuanjianGoujianShijian01/img/loader.gif
RuanjianGoujianShijian01/img/menu-icon.png
RuanjianGoujianShijian01/img/save.png
RuanjianGoujianShijian01/img/saved.png
RuanjianGoujianShijian01/img/settings-s.png
RuanjianGoujianShijian01/img/settings.png
RuanjianGoujianShijian01/img/star.png
RuanjianGoujianShijian01/js/__init__.py
RuanjianGoujianShijian01/js/epub.js
RuanjianGoujianShijian01/js/epub.min.js
RuanjianGoujianShijian01/js/epub.min.map
RuanjianGoujianShijian01/js/hooks.min.js
RuanjianGoujianShijian01/js/hooks.min.map
RuanjianGoujianShijian01/js/reader.js
RuanjianGoujianShijian01/js/reader.js.map
RuanjianGoujianShijian01/js/reader.min.js
RuanjianGoujianShijian01/js/reader.min.map
RuanjianGoujianShijian01/js/hooks/__init__.py
RuanjianGoujianShijian01/js/hooks/extensions/__init__.py
RuanjianGoujianShijian01/js/hooks/extensions/highlight.js
RuanjianGoujianShijian01/js/libs/__init__.py
RuanjianGoujianShijian01/js/libs/jquery.min.js
RuanjianGoujianShijian01/js/libs/localforage.min.js
RuanjianGoujianShijian01/js/libs/screenfull.js
ruanjian_goujian_shijian_0_1-2024.3.2.0.dist-info/METADATA
ruanjian_goujian_shijian_0_1-2024.3.2.0.dist-info/WHEEL
ruanjian_goujian_shijian_0_1-2024.3.2.0.dist-info/entry_points.txt
ruanjian_goujian_shijian_0_1-2024.3.2.0.dist-info/top_level.txt
ruanjian_goujian_shijian_0_1-2024.3.2.0.dist-info/RECORD
